{
  "tasks": [
    {
      "id": 1,
      "name": "task 01",
      "completed": false
    },
    {
      "id": 2,
      "name": "task 02",
      "completed": true
    },
    {
      "name": "task 01",
      "completed": false,
      "id": 3
    },
    {
      "name": "task 01",
      "completed": false,
      "id": 4
    },
    {
      "name": "task 01",
      "completed": false,
      "id": 5
    },
    {
      "name": "task 02",
      "completed": false,
      "id": 6
    },
    {
      "name": "task 03",
      "completed": false,
      "id": 7
    }
  ]
}
